MANIFEST.in
README.md
setup.cfg
setup.py
search_engine_scraper/__init__.py
search_engine_scraper/proxies.txt
search_engine_scraper/search_engine_scraper.py
search_engine_scraper/user_agents.txt
search_engine_scraper.egg-info/PKG-INFO
search_engine_scraper.egg-info/SOURCES.txt
search_engine_scraper.egg-info/dependency_links.txt
search_engine_scraper.egg-info/not-zip-safe
search_engine_scraper.egg-info/requires.txt
search_engine_scraper.egg-info/top_level.txt