Metadata-Version: 2.1
Name: search-engine-scraper
Version: 0.3
Summary: A module to scrape popular search engines
Home-page: https://github.com/deepsidh9/Search-Engine-Scraper
Author: Deep Singh Dhillon
Author-email: deep.barca@gmail.com
License: MIT
Platform: UNKNOWN
